.gitignore
MANIFEST.in
README.md
__init__.py
requirements.txt
setup.py
.github/ISSUE_TEMPLATE/bug_report.md
.github/ISSUE_TEMPLATE/feature_request.md
serendipity/__about__.py
serendipity/__init__.py
serendipity/interface.py
serendipity/translate_func.py
serendipity.egg-info/PKG-INFO
serendipity.egg-info/SOURCES.txt
serendipity.egg-info/dependency_links.txt
serendipity.egg-info/requires.txt
serendipity.egg-info/top_level.txt
tests/integration/basic_launch.py
tests/integration/ressources/test.py