Metadata-Version: 2.1
Name: serendipity
Version: 0.2.0
Summary: A multiprocessing module based on starting tmux sessions
Home-page: https://github.com/George3d6/serendipity
Author: George Hosu
Author-email: george@cerebralab.com
License: MIT
Download-URL: https://pypi.org/project/serendipity
Platform: UNKNOWN
Classifier: Programming Language :: Python :: 3
Classifier: License :: OSI Approved :: MIT License
Classifier: Operating System :: OS Independent
Requires-Python: >=3.6
